mcp_dispatch/__init__.py
mcp_dispatch/mcp_dispatch_service.py
mcp_dispatch/services/__init__.py
mcp_dispatch/services/dispatch_query.py
mcp_dispatch/services/dispatch_record.py
mcp_dispatch/utils/__init__.py
mcp_dispatch/utils/api.py
mcp_dispatch/utils/config.py
baiyx_mcp_server_dispatch-1.0.13.dist-info/METADATA
baiyx_mcp_server_dispatch-1.0.13.dist-info/WHEEL
baiyx_mcp_server_dispatch-1.0.13.dist-info/entry_points.txt
baiyx_mcp_server_dispatch-1.0.13.dist-info/RECORD
